[
  {
    "title": "فوائد لصقة الظهر الطبية",
    "content": "لصقة الظهر تساعد في تخفيف آلام العضلات والمفاصل والشد العضلي. تحتوي على مستخلصات طبيعية تحسن الدورة الدموية وتقلل الالتهابات.",
    "tags": "لصقة,ظهر,علاج,ألم"
  },
  {
    "title": "أفضل وقت لاستخدام لصقة المفاصل",
    "content": "يفضل وضع اللصقة بعد الاستحمام بماء دافئ، حيث تكون المسام مفتوحة ويُمتص المكون العلاجي بشكل أفضل. مدة الاستخدام الموصى بها 8 ساعات.",
    "tags": "مفاصل,لصقة,وقت"
  },
  {
    "title": "عروض وخصومات اللصقات الطبية",
    "content": "احصل على خصم 20% عند شراء عبوتين من لصقات المفاصل أو الظهر. العرض ساري حتى نهاية الشهر.",
    "tags": "خصم,عرض,شراء"
  },
  {
    "title": "كيفية الطلب",
    "content": "يمكنك الطلب مباشرة عبر الرسائل وسيتواصل معك المندوب لتأكيد العنوان والدفع عند الاستلام. التوصيل خلال 2-4 أيام.",
    "tags": "طلب,توصيل,مندوب"
  },
  {
    "title": "نصائح الاستخدام",
    "content": "تأكد من تنظيف المنطقة قبل وضع اللصقة، ولا تستخدمها على الجروح أو الجلد المتهيج. للاستخدام الخارجي فقط.",
    "tags": "نصائح,تحذير"
  }
]
